functions_by_jvefferson/README.md
functions_by_jvefferson/math_functions.py
functions_by_jvefferson-0.3.0.dist-info/WHEEL
functions_by_jvefferson-0.3.0.dist-info/METADATA
functions_by_jvefferson-0.3.0.dist-info/RECORD
